healthmetrics/__init__.py
healthmetrics/ard.py
healthmetrics/evaluation_context.py
healthmetrics/metric_define.py
healthmetrics/metric_evaluator.py
healthmetrics/metric_helpers.py
healthmetrics/metric_registry.py
healthmetrics/result_formatter.py
healthmetrics/table_formatter.py
healthmetrics/utils.py
healthmetrics-0.2.0.dist-info/licenses/LICENSE
healthmetrics-0.2.0.dist-info/METADATA
healthmetrics-0.2.0.dist-info/WHEEL
healthmetrics-0.2.0.dist-info/top_level.txt
healthmetrics-0.2.0.dist-info/RECORD
